README.md
setup.py
libpypro.egg-info/PKG-INFO
libpypro.egg-info/SOURCES.txt
libpypro.egg-info/dependency_links.txt
libpypro.egg-info/not-zip-safe
libpypro.egg-info/requires.txt
libpypro.egg-info/top_level.txt
libpythonpro/__init__.py
libpythonpro/github_api.py