Metadata-Version: 2.1
Name: libpypro
Version: 1.0
Summary: Módulo para exemplificar construção de projetos Python no curso PyTools
Home-page: https://github.com/kjuniors2/libpyhtonpro
Author: Lib Junior
Author-email: email@mail.com
License: GNU AFFERO GENERAL PUBLIC LICENSE
Platform: UNKNOWN
Classifier: Development Status :: 2 - Pre-Alpha
Classifier: Environment :: Console
Classifier: Intended Audience :: Developers
Classifier: License :: OSI Approved :: GNU Affero General Public License v3 or later (AGPLv3+)
Classifier: Operating System :: OS Independent
Classifier: Programming Language :: Python
Classifier: Framework :: Pytest
